MoDiSc/__init__.py
MoDiSc/packages.py
MoDiSc/plot_mcmc_results.py
MoDiSc/run_modisc.py
MoDiSc/emcee/__init__.py
MoDiSc/emcee/autocorr.py
MoDiSc/emcee/emcee_version.py
MoDiSc/emcee/ensemble.py
MoDiSc/emcee/interruptible_pool.py
MoDiSc/emcee/mh.py
MoDiSc/emcee/model.py
MoDiSc/emcee/mpi_pool.py
MoDiSc/emcee/pbar.py
MoDiSc/emcee/ptsampler.py
MoDiSc/emcee/sampler.py
MoDiSc/emcee/state.py
MoDiSc/emcee/tests.py
MoDiSc/emcee/utils.py
MoDiSc/emcee/backends/__init__.py
MoDiSc/emcee/backends/backend.py
MoDiSc/emcee/backends/hdf.py
MoDiSc/emcee/moves/__init__.py
MoDiSc/emcee/moves/de.py
MoDiSc/emcee/moves/de_snooker.py
MoDiSc/emcee/moves/gaussian.py
MoDiSc/emcee/moves/kde.py
MoDiSc/emcee/moves/mh.py
MoDiSc/emcee/moves/move.py
MoDiSc/emcee/moves/red_blue.py
MoDiSc/emcee/moves/stretch.py
MoDiSc/emcee/moves/walk.py
MoDiSc/emcee/tests/__init__.py
MoDiSc/emcee/tests/integration/__init__.py
MoDiSc/emcee/tests/integration/test_de.py
MoDiSc/emcee/tests/integration/test_de_snooker.py
MoDiSc/emcee/tests/integration/test_gaussian.py
MoDiSc/emcee/tests/integration/test_kde.py
MoDiSc/emcee/tests/integration/test_longdouble.py
MoDiSc/emcee/tests/integration/test_proposal.py
MoDiSc/emcee/tests/integration/test_stretch.py
MoDiSc/emcee/tests/integration/test_walk.py
MoDiSc/emcee/tests/unit/__init__.py
MoDiSc/emcee/tests/unit/test_autocorr.py
MoDiSc/emcee/tests/unit/test_backends.py
MoDiSc/emcee/tests/unit/test_blobs.py
MoDiSc/emcee/tests/unit/test_ensemble.py
MoDiSc/emcee/tests/unit/test_sampler.py
MoDiSc/emcee/tests/unit/test_state.py
MoDiSc/emcee/tests/unit/test_stretch.py
MoDiSc/functions/__init__.py
MoDiSc/functions/chisquare_test.py
MoDiSc/functions/dataset_load_and_process.py
MoDiSc/functions/mcmc_plot_results.py
MoDiSc/functions/noise_map_derive.py
MoDiSc/functions/parameters_rearrange_print.py
MoDiSc/functions/simulations.py
MoDiSc/functions/utils.py
MoDiSc-1.1.9.dist-info/METADATA
MoDiSc-1.1.9.dist-info/WHEEL
MoDiSc-1.1.9.dist-info/top_level.txt
MoDiSc-1.1.9.dist-info/RECORD
